cranet/__init__.py
cranet/autograd/__init__.py
cranet/autograd/function.py
cranet/autograd/grad_mode.py
cranet/autograd/random.py
cranet/autograd/tensor.py
cranet/autograd/utils.py
cranet/data/__init__.py
cranet/data/collate.py
cranet/data/dataloader.py
cranet/data/dataset.py
cranet/data/fetch.py
cranet/data/sampler.py
cranet/metrics/__init__.py
cranet/metrics/classification.py
cranet/metrics/common.py
cranet/metrics/image.py
cranet/nn/__init__.py
cranet/nn/functional.py
cranet/nn/init.py
cranet/nn/parameter.py
cranet/nn/utils.py
cranet/nn/modules/__init__.py
cranet/nn/modules/activation.py
cranet/nn/modules/batchnorm.py
cranet/nn/modules/container.py
cranet/nn/modules/conv.py
cranet/nn/modules/dropout.py
cranet/nn/modules/flatten.py
cranet/nn/modules/linear.py
cranet/nn/modules/loss.py
cranet/nn/modules/module.py
cranet/nn/modules/pooling.py
cranet/optim/__init__.py
cranet/optim/adam.py
cranet/optim/hebb.py
cranet/optim/learning_rule.py
cranet/optim/optimizer.py
cranet/optim/rmsprop.py
cranet/optim/sgd.py
cranet/utils/__init__.py
cranet/utils/pickle.py
cranet/utils/plot_model.py
cranet-0.2.0.dist-info/LICENSE
cranet-0.2.0.dist-info/METADATA
cranet-0.2.0.dist-info/WHEEL
cranet-0.2.0.dist-info/top_level.txt
cranet-0.2.0.dist-info/RECORD
